github_rename/__init__.py
github_rename/clidriver.py
github_rename-0.2.dist-info/.keep
github_rename-0.2.dist-info/DESCRIPTION.rst
github_rename-0.2.dist-info/METADATA
github_rename-0.2.dist-info/RECORD
github_rename-0.2.dist-info/WHEEL
github_rename-0.2.dist-info/entry_points.txt
github_rename-0.2.dist-info/metadata.json
github_rename-0.2.dist-info/top_level.txt
