Metadata-Version: 2.0
Name: github-rename
Version: 0.2
Summary: GitHub rename helper to change .git configs
Home-page: https://github.com/qqghst/GitHub-rename
Author: Qiushi Pan
Author-email: qqghst@gmail.com
License: MIT
Keywords: github git rename
Platform: UNKNOWN
Classifier: Environment :: Console
Classifier: Intended Audience :: Developers
Classifier: Operating System :: MacOS :: MacOS X
Classifier: Programming Language :: Python :: 3
Classifier: Programming Language :: Python :: 3.3
Classifier: Programming Language :: Python :: 3.4
Classifier: Programming Language :: Python :: 3.5
Classifier: Programming Language :: Python :: 3.6
Requires-Dist: click (>=6.7)
